devs_tracelogger/__init__.py
devs_tracelogger/log.py
devs_tracelogger/mongo.py
devs_tracelogger-0.3.0.dist-info/LICENCE
devs_tracelogger-0.3.0.dist-info/METADATA
devs_tracelogger-0.3.0.dist-info/WHEEL
devs_tracelogger-0.3.0.dist-info/top_level.txt
devs_tracelogger-0.3.0.dist-info/RECORD
