Metadata-Version: 2.1
Name: devs_tracelogger
Version: 0.3.0
Summary: Uma biblioteca para registrar logs e enviar notificações de erro para o Discord e MongoDB
Home-page: https://github.com/originalprecatorios/tracelogger
Author: Gelson Júnior
Author-email: gelson.junior@grupobachega.com.br
Classifier: Programming Language :: Python :: 3
Classifier: License :: OSI Approved :: MIT License
Classifier: Operating System :: OS Independent
Requires-Python: >=3.6
License-File: LICENCE
Requires-Dist: requests
Requires-Dist: pymongo
